CHANGELOG.md
kedro_neptune/__init__.py
kedro_neptune/config.py
kedro_neptune/utils.py
kedro_neptune/version.py
kedro_neptune-0.6.0.dist-info/LICENSE
kedro_neptune-0.6.0.dist-info/METADATA
kedro_neptune-0.6.0.dist-info/WHEEL
kedro_neptune-0.6.0.dist-info/entry_points.txt
kedro_neptune-0.6.0.dist-info/RECORD
